qctrlworkflowclient/__init__.py
qctrlworkflowclient/defaults.py
qctrlworkflowclient/functions.py
qctrlworkflowclient/products.py
qctrlworkflowclient/router/__init__.py
qctrlworkflowclient/router/api.py
qctrlworkflowclient/router/base.py
qctrlworkflowclient/router/local.py
qctrlworkflowclient/settings.py
qctrlworkflowclient/utils.py
qctrl_workflow_client-9.0.1.dist-info/LICENSE
qctrl_workflow_client-9.0.1.dist-info/METADATA
qctrl_workflow_client-9.0.1.dist-info/WHEEL
qctrl_workflow_client-9.0.1.dist-info/RECORD
